pyopnsenseapi/__init__.py
pyopnsenseapi/const.py
pyopnsenseapi/modules/__init__.py
pyopnsenseapi/modules/client.py
pyopnsenseapi/modules/common.py
pyopnsenseapi/modules/enums.py
pyopnsenseapi/modules/core/__init__.py
pyopnsenseapi/modules/core/const.py
pyopnsenseapi/modules/core/firmware.py
pyopnsenseapi/modules/core/service.py
pyopnsenseapi/modules/core/system.py
pyopnsenseapi/modules/diagnostics/__init__.py
pyopnsenseapi/modules/diagnostics/activity.py
pyopnsenseapi/modules/diagnostics/const.py
pyopnsenseapi/modules/diagnostics/dns.py
pyopnsenseapi/modules/diagnostics/dns_diagnostics.py
pyopnsenseapi/modules/diagnostics/firewall.py
pyopnsenseapi/modules/diagnostics/interface.py
pyopnsenseapi/modules/diagnostics/netflow.py
pyopnsenseapi/modules/diagnostics/networkinsight.py
pyopnsenseapi/modules/diagnostics/packet_capture.py
pyopnsenseapi/modules/diagnostics/system.py
pyopnsenseapi/modules/diagnostics/systemhealth.py
pyopnsenseapi/modules/diagnostics/traffic.py
pyopnsenseapi-0.1.1.dist-info/LICENSE
pyopnsenseapi-0.1.1.dist-info/METADATA
pyopnsenseapi-0.1.1.dist-info/WHEEL
pyopnsenseapi-0.1.1.dist-info/top_level.txt
pyopnsenseapi-0.1.1.dist-info/RECORD
