Metadata-Version: 2.1
Name: pyopnsenseapi
Version: 0.1.1
Summary: Another Python OPNsense API library
Home-page: https://github.com/11harveyj/pyopnsenseapi
Project-URL: Bug Tracker, https://github.com/11harveyj/pyopnsenseapi/issues
Project-URL: Changelog, https://github.com/11harveyj/pyopnsenseapi/releases
Classifier: Programming Language :: Python :: 3
Classifier: License :: OSI Approved :: BSD License
Classifier: Intended Audience :: Developers
License-File: LICENSE
